[
  {
    "account": "yunxinqianao@163.com",
    "password": "H1NQUBMuNS",
    "region": ""
  },
  {
    "account": "yijieben555555@163.com",
    "password": "Z2Qk5L@J",
    "region": ""
  },
  {
    "account": "jiaoweiqianqian@163.com",
    "password": "Ouk6688tt",
    "region": ""
  },
  {
    "account": "toddcopthorne@mail.com",
    "password": "9LAGTd!k",
    "region": ""
  },
  {
    "account": "chasschmidt51060@gmail.com",
    "password": "Zm115566",
    "region": "美国"
  },
  {
    "account": "sullivandyer3791@gmail.com",
    "password": "Jr18Sh32",
    "region": "美国"
  },
  {
    "account": "Mollyn2592@icloud.com",
    "password": "96FpEqfRMh",
    "region": ""
  },
  {
    "account": "oubi9999999999@163.com",
    "password": "jPpJmC9ebf",
    "region": ""
  },
  {
    "account": "Laurenq2682@icloud.com",
    "password": "dHxcVxFq5y",
    "region": ""
  },
  {
    "account": "jushao777777@163.com",
    "password": "YfDkGfG3gb",
    "region": "美国"
  },
  {
    "account": "jiutu3333333@163.com",
    "password": "T8KXk7X6kj",
    "region": "美国"
  },
  {
    "account": "jiuyi99999999@163.com",
    "password": "33hHQHxVtg",
    "region": "美国"
  },
  {
    "account": "jume333333@163.com",
    "password": "y5Eta9PkAF",
    "region": "美国"
  },
  {
    "account": "jixi7777777@163.com",
    "password": "Pb7EUtKhmd",
    "region": "美国"
  },
  {
    "account": "tjaimeflores85a@gmx.pt",
    "password": "HWqkUynFt1",
    "region": ""
  },
  {
    "account": "maryamwkebrooksdtt@gmail.com",
    "password": "hPPv6V3Ve4",
    "region": ""
  },
  {
    "account": "hccfqbwhsn9115@hotmail.com",
    "password": "vnPj6jfZMN",
    "region": ""
  },
  {
    "account": "ftnhijwuyw731@hotmail.com",
    "password": "6jdMpyWxA5",
    "region": ""
  },
  {
    "account": "auroragrimes7@gmail.com",
    "password": "n6!r48AY",
    "region": ""
  },
  {
    "account": "franciscoojohnstonalkpz@gmail.com",
    "password": "Bv20Et64",
    "region": "美国"
  },
  {
    "account": "kaylafguzmans8b2x@gmail.com",
    "password": "Bc21Bu93",
    "region": "美国"
  },
  {
    "account": "woodta56@gmail.com",
    "password": "Dd1a0b922",
    "region": ""
  }
]