[
  {
    "account": "vndoh67101@outlook.com",
    "password": "E2v7bKJKvb",
    "region": ""
  },
  {
    "account": "rdieta.ssums0@icloud.com",
    "password": "HjWrA1taus",
    "region": ""
  },
  {
    "account": "melaniehan3superf@icloud.com",
    "password": "TDB9c4ZCbv2E",
    "region": ""
  },
  {
    "account": "mogymoino@hotmail.com",
    "password": "JEaDM@g9",
    "region": ""
  },
  {
    "account": "jaydenbwolson@hotmail.com",
    "password": "SDg17n22",
    "region": ""
  },
  {
    "account": "linasmittle@outlook.com",
    "password": "eKSP&I1C",
    "region": ""
  },
  {
    "account": "saffiewhitescarver@outlook.com",
    "password": "9o9&xKbz",
    "region": ""
  },
  {
    "account": "gillman.redman66435@legendary.it.com",
    "password": "lz!SLY9D",
    "region": ""
  },
  {
    "account": "erika.sontag20598@isss.it.com",
    "password": "0K&Ox80P",
    "region": ""
  },
  {
    "account": "hanseljodelle@gmail.com",
    "password": "nH7p!wVc",
    "region": ""
  },
  {
    "account": "mcmillanenrique4@gmail.com",
    "password": "xG6@WEvR",
    "region": ""
  },
  {
    "account": "yrdjdariofisher@gmail.com",
    "password": "X6XYkp8FP7",
    "region": "美国"
  },
  {
    "account": "masonallenbv0384@gmail.com",
    "password": "Mb5uSRskQM",
    "region": "英国"
  },
  {
    "account": "azumi.bhoomr6@icloud.com",
    "password": "RQYd5d1aGS",
    "region": "美国"
  },
  {
    "account": "michaelbennettqoho2@gmail.com",
    "password": "rsQ2BsVtEf",
    "region": "美国"
  },
  {
    "account": "savitaj149@infornma.com",
    "password": "4qxDAG5h5v",
    "region": "美国"
  },
  {
    "account": "qfqr14202@outlook.com",
    "password": "7CDBWbnxwB",
    "region": ""
  },
  {
    "account": "mcclurecssndr@gmail.com",
    "password": "@fO8SkzI",
    "region": ""
  },
  {
    "account": "divankolakg1@hotmail.com",
    "password": "zN2oO0#i",
    "region": ""
  },
  {
    "account": "cemende96@gmail.com",
    "password": "Dd1bec01b",
    "region": ""
  },
  {
    "account": "delissakrystine@gmail.com",
    "password": "Dd1c493e0",
    "region": ""
  },
  {
    "account": "rayannafeinstein8mcx62@gmail.com",
    "password": "!x3oD2MM",
    "region": ""
  },
  {
    "account": "qfvblj2968@163.com",
    "password": "T9qzMZhAxq",
    "region": "中国大陆"
  },
  {
    "account": "qian2007495zhan@163.com",
    "password": "h9BW5EzbWS",
    "region": "美国"
  }
]