[
  {
    "account": "iefaliyacordova@gmail.com",
    "password": "3vFScqDBjn",
    "region": ""
  },
  {
    "account": "jefferyhwj255@gmail.com",
    "password": "mbq5rFncvr",
    "region": ""
  },
  {
    "account": "winnygindlespergergc4787@gmail.com",
    "password": "tr85qUGY84",
    "region": ""
  },
  {
    "account": "fzu572sj18xp2n@boycpu.com",
    "password": "44s41amJ4xth4h",
    "region": " 美国 "
  },
  {
    "account": "selvaggioariagna882@gmail.com",
    "password": "g#S3mBeZ",
    "region": ""
  },
  {
    "account": "yuzhimi8499142@hotmail.com",
    "password": "vls!I550",
    "region": ""
  },
  {
    "account": "ejcuizon_milag064@icloud.com",
    "password": "rD26hJpt2S",
    "region": "美国"
  },
  {
    "account": "hudson1acole@outlook.com",
    "password": "5gZ7z9nwSb",
    "region": "美国"
  },
  {
    "account": "herthiazitzmannfn9252@gmail.com",
    "password": "jwrsqahJ2p",
    "region": "美国"
  },
  {
    "account": "catherinexvqc27@gmail.com",
    "password": "Av112211",
    "region": "越南"
  },
  {
    "account": "henryfemsg@outlook.com",
    "password": "yJjh3mAs8t",
    "region": "越南"
  },
  {
    "account": "huertagrace86@gmail.com",
    "password": "MxyU1yCv5D",
    "region": "香港"
  },
  {
    "account": "oscar50sumhin@outlook.com",
    "password": "Ax112211",
    "region": "美国"
  },
  {
    "account": "wadeniemeyerft8035@gmail.com",
    "password": "RxKhHbQP3w",
    "region": "美国"
  },
  {
    "account": "d15i0urhrod3ig@logpe.com",
    "password": "J9fvYfYk5n",
    "region": "美国"
  },
  {
    "account": "jdwtxexlwwhivn@outlook.com",
    "password": "r#eAvY0V",
    "region": ""
  },
  {
    "account": "haasketesmeralda@gmail.com",
    "password": "42kSAMvgCw",
    "region": ""
  },
  {
    "account": "aletheacantorejx4711@gmail.com",
    "password": "6rGURazWWc",
    "region": ""
  },
  {
    "account": "REBELPRIDE79@hotmail.com",
    "password": "9pRuDMM3yy",
    "region": "美国"
  },
  {
    "account": "qgb477203@163.com",
    "password": "UpHchHCNv5",
    "region": "美国"
  },
  {
    "account": "qian2007495zhan@163.com",
    "password": "2TZKquYje7",
    "region": "美国"
  },
  {
    "account": "qfpcwzp942@163.com",
    "password": "8MvzMFj7Xv",
    "region": "美国"
  },
  {
    "account": "qfvblj2968@163.com",
    "password": "tFJqXpYwR5",
    "region": "香港"
  }
]