[
  {
    "account": "rdieta.ssums0@icloud.com",
    "password": "B6zNsnBn6M",
    "region": ""
  },
  {
    "account": "danielshaw5ea@hotmail.com",
    "password": "r2@wlmG3",
    "region": ""
  },
  {
    "account": "jaydenbwolson@hotmail.com",
    "password": "SDg17n22",
    "region": ""
  },
  {
    "account": "somerknackvipus@outlook.com",
    "password": "f!1tUXgb",
    "region": ""
  },
  {
    "account": "saffiewhitescarver@outlook.com",
    "password": "#OwdN8wl",
    "region": ""
  },
  {
    "account": "gillman.redman66435@legendary.it.com",
    "password": "dQ#lfaW0",
    "region": ""
  },
  {
    "account": "hanseljodelle@gmail.com",
    "password": "DnVkY1#2",
    "region": ""
  },
  {
    "account": "ykyla4374@gmail.com",
    "password": "GF!1qF!a",
    "region": ""
  },
  {
    "account": "yrdjdariofisher@gmail.com",
    "password": "3j8fSkmZPV",
    "region": "美国"
  },
  {
    "account": "savitaj149@infornma.com",
    "password": "3yr9C4bpNG",
    "region": "美国"
  },
  {
    "account": "masonallenbv0384@gmail.com",
    "password": "z4wevUY3dj",
    "region": "英国"
  },
  {
    "account": "azumi.bhoomr6@icloud.com",
    "password": "tdxRAeAvR3",
    "region": "美国"
  },
  {
    "account": "michaelbennettqoho2@gmail.com",
    "password": "HcVD7HtVPd",
    "region": "美国"
  },
  {
    "account": "i7t0w5xiyjr@outlook.com",
    "password": "dWvrDfm7hH",
    "region": ""
  },
  {
    "account": "hotcars964allison@icloud.com",
    "password": "Dd1de1a9f",
    "region": "检测中"
  },
  {
    "account": "woodta56@gmail.com",
    "password": "Dd12f7e76",
    "region": ""
  },
  {
    "account": "rayannafeinstein8mcx62@gmail.com",
    "password": "3@tUZeYN",
    "region": ""
  },
  {
    "account": "qfvblj2968@163.com",
    "password": "yU5ZJEtFB3",
    "region": "中国大陆"
  },
  {
    "account": "qian2007495zhan@163.com",
    "password": "pNhUvmk8Ev",
    "region": "美国"
  }
]