[
  {
    "account": "graceelijah689gmlv@gmail.com",
    "password": "pXWbZR1tw9",
    "region": ""
  },
  {
    "account": "wyattlanene9@outlook.com",
    "password": "TDJTsdWkFUp9",
    "region": ""
  },
  {
    "account": "yuanyeguahanji@163.com",
    "password": "TDvyddbw85Pt",
    "region": ""
  },
  {
    "account": "esmeihxwarduqf@gmail.com",
    "password": "TDS3j4Treukz",
    "region": ""
  },
  {
    "account": "qixun5555555@163.com",
    "password": "TDP9tzPvYGCw",
    "region": ""
  },
  {
    "account": "michaelsuqhh@outlook.com",
    "password": "TDJaHN1Cjjy5",
    "region": ""
  },
  {
    "account": "hetu8888888888@163.com",
    "password": "TDQTj8kPKFhA",
    "region": ""
  },
  {
    "account": "hocineomerzof@hotmail.com",
    "password": "5!sGMxSY",
    "region": ""
  },
  {
    "account": "oubi9999999999@163.com",
    "password": "XPSUhexDY9",
    "region": ""
  },
  {
    "account": "Mollyn2592@icloud.com",
    "password": "H2FseutNT4",
    "region": ""
  },
  {
    "account": "Laurenq2682@icloud.com",
    "password": "XBDVdU55M6",
    "region": ""
  },
  {
    "account": "jiuyi99999999@163.com",
    "password": "5fQpskyEEf",
    "region": "美国"
  },
  {
    "account": "jushao777777@163.com",
    "password": "YfDkGfG3gb",
    "region": "美国"
  },
  {
    "account": "jume333333@163.com",
    "password": "4tTYqDHq6v",
    "region": "美国"
  },
  {
    "account": "jixi7777777@163.com",
    "password": "Tkfg2BUwbN",
    "region": "美国"
  },
  {
    "account": "jiutu3333333@163.com",
    "password": "vJsDRS3vTA",
    "region": "美国"
  },
  {
    "account": "mobrewer65025@gmail.com",
    "password": "Dd1364d9b",
    "region": ""
  }
]