[
  {
    "account": "saub69@hotmail.com",
    "password": "Wc19Pk57",
    "region": ""
  },
  {
    "account": "p3@7777.live",
    "password": "HaiHuaz9X6AwAq4S",
    "region": ""
  },
  {
    "account": "p7@7777.live",
    "password": "HaiHuabmYvj3cgn4",
    "region": ""
  },
  {
    "account": "p12@7777.live",
    "password": "HaiHuaJ7FJP9qFqz",
    "region": ""
  },
  {
    "account": "p13@7777.live",
    "password": "HaiHuanrE8mWX36Z",
    "region": ""
  },
  {
    "account": "xamksvmy@outlook.com",
    "password": "FreG2a6GnU",
    "region": ""
  },
  {
    "account": "casbygangax7@hotmail.com",
    "password": "j21SDnQrKc",
    "region": ""
  },
  {
    "account": "imbroisittc4@hotmail.com",
    "password": "HWFcMR4xJz",
    "region": ""
  },
  {
    "account": "ferraracciotara2503@outlook.com",
    "password": "SBkj5Ftgu7",
    "region": ""
  },
  {
    "account": "alethiadauenhauerus@outlook.com",
    "password": "WAyD227EZy",
    "region": ""
  },
  {
    "account": "LedbetterVienna1065@icloud.com",
    "password": "s7Dep9PXks",
    "region": ""
  },
  {
    "account": "ArtistaVita432@icloud.com",
    "password": "xqR2N5EAh8",
    "region": ""
  },
  {
    "account": "btauaxv@outlook.com",
    "password": "44s42JqZkBz5kx",
    "region": " 美国 "
  },
  {
    "account": "facilisi_sa.t2@icloud.com",
    "password": "TDntKJk2pKSh",
    "region": ""
  },
  {
    "account": "alyot1@gmail.com",
    "password": "TD4HCJ1f1JqT",
    "region": ""
  },
  {
    "account": "ekarinf@yahoo.com",
    "password": "TDHe7yTZcpSS",
    "region": ""
  },
  {
    "account": "jaydenbwolson@hotmail.com",
    "password": "SDg17n22",
    "region": ""
  },
  {
    "account": "malonegghhkyleigh@gmail.com",
    "password": "idgDoR8&",
    "region": ""
  },
  {
    "account": "louisobrien08041@gmail.com",
    "password": "bN2g!8lI",
    "region": ""
  },
  {
    "account": "kreinsigmunds2477@outlook.com",
    "password": "1!Lo!K1b",
    "region": ""
  },
  {
    "account": "loribeth351o@eyepaste.com",
    "password": "B3p!XBez",
    "region": ""
  },
  {
    "account": "8ky6xr799k79f6@twopc.com",
    "password": "DdBMW60b6",
    "region": ""
  },
  {
    "account": "robertpijperss@icloud.com",
    "password": "m6tXjsFp1B",
    "region": "美国"
  },
  {
    "account": "mrxxrqb@outlook.com",
    "password": "zP6uVFQb6V",
    "region": ""
  },
  {
    "account": "xajgmq@outlook.com",
    "password": "SyM15AsrNZ",
    "region": ""
  },
  {
    "account": "brittney.smith035@iCloud.com",
    "password": "1arn49NX3M",
    "region": ""
  },
  {
    "account": "olivergfwrleonard@gmail.com",
    "password": "Iu6DEYh@",
    "region": ""
  },
  {
    "account": "kdjqcwqtkca@outlook.com",
    "password": "halsh?Dd123453c",
    "region": ""
  },
  {
    "account": "rhianaanneka@gmail.com",
    "password": "Dd197d66b",
    "region": ""
  },
  {
    "account": "rhvhjaquanpetty@gmail.com",
    "password": "24daVQZwgV",
    "region": ""
  },
  {
    "account": "romuloshauffng3135@gmail.com",
    "password": "w72SVWUp4S",
    "region": ""
  },
  {
    "account": "kmsdisabellachan@gmail.com",
    "password": "tB4AQN1hRR",
    "region": ""
  },
  {
    "account": "jarvisgerald39@gmail.com",
    "password": "m6ucK1k9Nr",
    "region": ""
  }
]