[
  {
    "account": "2696219804@qq.com",
    "password": "PCKS8xAmdC",
    "region": ""
  },
  {
    "account": "jonlucerofn531@gmail.com",
    "password": "eUgFbGzN1f",
    "region": ""
  },
  {
    "account": "3392483535@qq.com",
    "password": "HZR132GXz9",
    "region": ""
  },
  {
    "account": "markishaneda@gmail.com",
    "password": "ZTH6mMfNCJ",
    "region": ""
  },
  {
    "account": "riokacedi@outlook.com",
    "password": "Qj4x9JhXFV",
    "region": ""
  },
  {
    "account": "n_sadipscingclas0@icloud.com",
    "password": "4FPMNGhJ3A",
    "region": ""
  },
  {
    "account": "3498871513@qq.com",
    "password": "6krQcqaJdH",
    "region": ""
  },
  {
    "account": "qlh369hlq@163.com",
    "password": "1RPpFpFt89",
    "region": ""
  },
  {
    "account": "elizaqroriverafkr@gmail.com",
    "password": "AwTgEJUxx6",
    "region": ""
  },
  {
    "account": "ww0tG14HQHU311@hotmail.com",
    "password": "8Yx2SjcqFb",
    "region": ""
  },
  {
    "account": "Hitt93whef@gmail.com",
    "password": "1AebdJRfDj",
    "region": ""
  },
  {
    "account": "Kingsley0509yel@gmail.com",
    "password": "MBbN8542",
    "region": ""
  },
  {
    "account": "ptxrff@163.com",
    "password": "ZfYANFgW1c",
    "region": ""
  },
  {
    "account": "k73trd@163.com",
    "password": "tRb8aMU4BS",
    "region": ""
  },
  {
    "account": "Gomez0509yel@gmail.com",
    "password": "WNhn4ZAu5T",
    "region": ""
  },
  {
    "account": "wxvgqnnuu@outlook.com",
    "password": "TDwZvB8mzDxv",
    "region": ""
  },
  {
    "account": "ehfgwdpwg@outlook.com",
    "password": "mKxg@@63",
    "region": ""
  },
  {
    "account": "cranstondittoahmpfl1e163q@outlook.com",
    "password": "Nb557788",
    "region": ""
  },
  {
    "account": "terri7035hayes@yandex.com",
    "password": "40s5PQ!x",
    "region": ""
  },
  {
    "account": "agang130902783116@icloud.com",
    "password": "Dd100d7d0",
    "region": ""
  },
  {
    "account": "azumi.bhoomr6@icloud.com",
    "password": "Ch2zmnj8Rh",
    "region": "美国"
  },
  {
    "account": "yrdjdariofisher@gmail.com",
    "password": "5zzWTmvYVH",
    "region": "美国"
  },
  {
    "account": "laurenstierjq7035@gmail.com",
    "password": "987dSRVQMn",
    "region": "美国"
  },
  {
    "account": "sarahdoolittle551881@gmail.com",
    "password": "zz9CmKSXmF",
    "region": "美国"
  },
  {
    "account": "vxzlxoi1176y@outlook.com",
    "password": "Ncyke5pDRv",
    "region": "美国"
  },
  {
    "account": "lanlong65@163.com",
    "password": "3UtDTVduZf",
    "region": ""
  },
  {
    "account": "Tibbetts3052mrkl@gmail.com",
    "password": "Tibbetts3052mrkl@gmail.com",
    "region": ""
  },
  {
    "account": "miastnley@gmail.com",
    "password": "Dd16ce0d8",
    "region": ""
  },
  {
    "account": "queatnascet28@icloud.com",
    "password": "cb7MRJ7EC7",
    "region": "美国"
  },
  {
    "account": "is.icura_bit48442@icloud.com",
    "password": "D2a2EEqUvP",
    "region": "美国"
  },
  {
    "account": "bierospharet64905@icloud.com",
    "password": "HfaqhsCjc6",
    "region": "美国"
  },
  {
    "account": "umrho.ncus.mae381@icloud.com",
    "password": "RBSGTx4jcb",
    "region": "美国"
  },
  {
    "account": "veren.merkson_ge4@icloud.com",
    "password": "Qatc1heu3E",
    "region": "美国"
  }
]