[
  {
    "account": "leooscar576wbxj@gmail.com",
    "password": "Bdf7dnK48H",
    "region": ""
  },
  {
    "account": "pnbksrhy981@hotmail.com",
    "password": "R2Hm3dA36z",
    "region": ""
  },
  {
    "account": "rmokpxmd190@hotmail.com",
    "password": "wN8sVC5hn2",
    "region": ""
  },
  {
    "account": "hjlnrsw1535@hotmail.com",
    "password": "B4H8ckQ2sw",
    "region": ""
  },
  {
    "account": "minhh222@163.com",
    "password": "PgTjqRrG3T",
    "region": ""
  },
  {
    "account": "vtvybhr0216@hotmail.com",
    "password": "JCDbaTkt75",
    "region": ""
  },
  {
    "account": "yjagtitu2750@hotmail.com",
    "password": "UaxcF3DMcH",
    "region": ""
  },
  {
    "account": "cjbyurd8028@hotmail.com",
    "password": "Es123123",
    "region": ""
  },
  {
    "account": "kkqgmdfgf128@hotmail.com",
    "password": "Es123123",
    "region": ""
  },
  {
    "account": "sebroknievebyl@hotmail.com",
    "password": "a9BBK2uP98",
    "region": ""
  },
  {
    "account": "yuanxiaqunguaix@163.com",
    "password": "TDaaZxj76dMt",
    "region": ""
  },
  {
    "account": "dujieyou111111@163.com",
    "password": "TDBv6RGCtYU1",
    "region": ""
  },
  {
    "account": "lucap6aowensck5@gmail.com",
    "password": "TDx52d2kPkvq",
    "region": ""
  },
  {
    "account": "mohammedsl9wellspby@gmail.com",
    "password": "TD6tBNHYmQ7A",
    "region": ""
  },
  {
    "account": "elliezcdmooretvd@gmail.com",
    "password": "TDaJu2WECnad",
    "region": ""
  },
  {
    "account": "meganwedkingrqr@gmail.com",
    "password": "TDmRtw1v91F1",
    "region": ""
  },
  {
    "account": "nancy34bgonzalezwnn@gmail.com",
    "password": "TDQpJxQ7EedB",
    "region": ""
  },
  {
    "account": "maxkruwoodsvto@gmail.com",
    "password": "TD773sSSBSbw",
    "region": ""
  },
  {
    "account": "harriet1lvgriffin3rh@gmail.com",
    "password": "TDaqY361vKfF",
    "region": ""
  },
  {
    "account": "michaelsuqhh@outlook.com",
    "password": "TDHGvs4Ab1Dp",
    "region": ""
  },
  {
    "account": "jushao777777@163.com",
    "password": "9pj8gXC4xz",
    "region": ""
  },
  {
    "account": "jixi7777777@163.com",
    "password": "h5t8y74r1P",
    "region": ""
  },
  {
    "account": "fcvfugi1820071@outlook.com",
    "password": "wS11jgmea9",
    "region": ""
  },
  {
    "account": "laihe1111111@163.com",
    "password": "TD9yf5UXFrbm",
    "region": ""
  },
  {
    "account": "haydllo999@gmail.com",
    "password": "Dd133ec6c",
    "region": ""
  },
  {
    "account": "callumu14sullivanyj3@gmail.com",
    "password": "nvYN7k4Vs8",
    "region": ""
  },
  {
    "account": "mincyneyver@hotmail.com",
    "password": "D6mxTDy4H5",
    "region": ""
  },
  {
    "account": "chikan662200@163.com",
    "password": "y2VUDBU4PH",
    "region": ""
  },
  {
    "account": "vuk823084062@163.com",
    "password": "jCqTNKP9mq",
    "region": ""
  },
  {
    "account": "bushi68400848@163.com",
    "password": "wtPT6G4jyx",
    "region": ""
  },
  {
    "account": "shaoye2442048@163.com",
    "password": "7aPbfkWg5G",
    "region": ""
  },
  {
    "account": "jttvddwxz0694@hotmail.com",
    "password": "EbVeAu3Awx",
    "region": ""
  },
  {
    "account": "BiancaIsaac24016@icloud.com",
    "password": "PfPBMwVkD7",
    "region": ""
  },
  {
    "account": "muyalawenda@hotmail.com",
    "password": "AQXrUUy7Du",
    "region": ""
  }
]