[
  {
    "account": "ftnhijwuyw731@hotmail.com",
    "password": "dk9u3uVFdW",
    "region": ""
  },
  {
    "account": "linai648626262@163.com",
    "password": "TDukZygc52mf",
    "region": ""
  },
  {
    "account": "beixi462086620@163.com",
    "password": "TDWsTj398v8a",
    "region": ""
  },
  {
    "account": "bameng08228@163.com",
    "password": "TDCsM7VTfyzx",
    "region": ""
  },
  {
    "account": "xilang242@163.com",
    "password": "TDyA7BZqsXHr",
    "region": ""
  },
  {
    "account": "shaotuo882@163.com",
    "password": "TD1mtZxBNkax",
    "region": ""
  },
  {
    "account": "rennai55555@163.com",
    "password": "TDCcp4fSHHTG",
    "region": ""
  },
  {
    "account": "tongshi33333@163.com",
    "password": "TDkUqt9NXNz8",
    "region": ""
  },
  {
    "account": "heye286002660@163.com",
    "password": "TDgTfsZeUyq9",
    "region": ""
  },
  {
    "account": "chuiyu422004@163.com",
    "password": "TDyeBYq452kP",
    "region": ""
  },
  {
    "account": "moudou6404@163.com",
    "password": "TDC4WPxPyUw9",
    "region": ""
  },
  {
    "account": "yuanyeguahanji@163.com",
    "password": "TD3gHjWdQPhh",
    "region": ""
  },
  {
    "account": "youzai082046@163.com",
    "password": "TDTmYf8X43sZ",
    "region": ""
  },
  {
    "account": "dun88668044@163.com",
    "password": "TDxzpmy2JUR2",
    "region": ""
  },
  {
    "account": "handilu284484@163.com",
    "password": "TDzYsNr1PhC6",
    "region": ""
  },
  {
    "account": "qixun5555555@163.com",
    "password": "TDuFS6868Kvu",
    "region": ""
  },
  {
    "account": "michaelsuqhh@outlook.com",
    "password": "123654789qqQ",
    "region": ""
  },
  {
    "account": "canggua08660@163.com",
    "password": "TDVJJgfhCWB2",
    "region": ""
  },
  {
    "account": "Laurenq2682@icloud.com",
    "password": "XcKJPQ4wQ2",
    "region": ""
  },
  {
    "account": "oubi9999999999@163.com",
    "password": "7YY5ya4Hqn",
    "region": ""
  },
  {
    "account": "Mollyn2592@icloud.com",
    "password": "JM59VYhb9X",
    "region": ""
  },
  {
    "account": "mobrewer65025@gmail.com",
    "password": "Dd183ca65",
    "region": ""
  }
]