[
  {
    "account": "daiesther1vk@hotmail.com",
    "password": "9W8MP2QvqG",
    "region": ""
  },
  {
    "account": "yunxinqianao@163.com",
    "password": "PqpfbN37FD",
    "region": ""
  },
  {
    "account": "chloedvpowellgl@gmail.com",
    "password": "vnxRF6b9Cv",
    "region": ""
  },
  {
    "account": "lynette.mckinney@boxrar.com",
    "password": "5hl4&4AK",
    "region": ""
  },
  {
    "account": "kanlu333333333@163.com",
    "password": "x!O3x1Fj",
    "region": ""
  },
  {
    "account": "duzhang888888@163.com",
    "password": "yDC29y!P",
    "region": ""
  },
  {
    "account": "wyattgibbsjaydin@gmail.com",
    "password": "b&PO8Qej",
    "region": ""
  },
  {
    "account": "franciscoojohnstonalkpz@gmail.com",
    "password": "Qg37Wt84",
    "region": "美国"
  },
  {
    "account": "haroldpfernandeztxvdv@gmail.com",
    "password": "Cx43Qy44",
    "region": "美国"
  },
  {
    "account": "oubi9999999999@163.com",
    "password": "j5HGpQtgaz",
    "region": ""
  },
  {
    "account": "Mollyn2592@icloud.com",
    "password": "PaVafJGyy6",
    "region": ""
  },
  {
    "account": "Laurenq2682@icloud.com",
    "password": "qbSuAaq1nK",
    "region": ""
  },
  {
    "account": "ssom1017@hotmail.com",
    "password": "8ecgFg!6",
    "region": ""
  },
  {
    "account": "lancerowe15958@gmail.com",
    "password": "Sy64Kn11",
    "region": "美国"
  },
  {
    "account": "haydllo999@gmail.com",
    "password": "Dd1dd0e75",
    "region": ""
  }
]