[
  {
    "account": "leeesk62701@icloud.com",
    "password": "D3RDSgYj3P",
    "region": ""
  },
  {
    "account": "lindaodw27786@icloud.com",
    "password": "1FHXdxxGSm",
    "region": ""
  },
  {
    "account": "ogurandy44131@icloud.com",
    "password": "pvBeMy9FCM",
    "region": ""
  },
  {
    "account": "reginaamx00410@icloud.com",
    "password": "W3vnPYsSmd",
    "region": ""
  },
  {
    "account": "brigittejpx20705@icloud.com",
    "password": "WN3uJtwthY",
    "region": ""
  },
  {
    "account": "christaxki84479@icloud.com",
    "password": "DeGSSa6gfY",
    "region": ""
  },
  {
    "account": "nikkisla35062@icloud.com",
    "password": "15ymuA4WVH",
    "region": ""
  },
  {
    "account": "rjnwilliam56367@icloud.com",
    "password": "uEUa5gBty3",
    "region": ""
  },
  {
    "account": "vnrroger55629@icloud.com",
    "password": "5AJBKr9UFw",
    "region": ""
  },
  {
    "account": "ffyglenda03622@icloud.com",
    "password": "4gcu2GN28c",
    "region": ""
  },
  {
    "account": "qcpenrique23543@icloud.com",
    "password": "5xR2WN4Q9e",
    "region": ""
  },
  {
    "account": "robertoxbe53275@icloud.com",
    "password": "T1vRsqzKbp",
    "region": ""
  },
  {
    "account": "dorothyvma13664@icloud.com",
    "password": "JV3z3N2nEX",
    "region": ""
  },
  {
    "account": "alexisjohnmays6r6@icloud.com",
    "password": "Xzhm8jzTvx",
    "region": ""
  },
  {
    "account": "xyumaria92408@icloud.com",
    "password": "qHZX5sTWdx",
    "region": ""
  },
  {
    "account": "Orvexilad5Pto@icloud.com",
    "password": "m9erKTtBdH",
    "region": ""
  },
  {
    "account": "Raxodivle4Kpa@icloud.com",
    "password": "dtFkx8sMvB",
    "region": ""
  },
  {
    "account": "Quvexiral7Mto@icloud.com",
    "password": "4ffvN3eP9C",
    "region": ""
  },
  {
    "account": "nbrvc11222@hotmail.com",
    "password": "RVdE5JjDWs",
    "region": ""
  },
  {
    "account": "dpkjknd45561@hotmail.com",
    "password": "UnM6JFrANs",
    "region": ""
  },
  {
    "account": "jessrmm19102@icloud.com",
    "password": "C7V4xEYSBF",
    "region": ""
  },
  {
    "account": "charolettezyu56172@icloud.com",
    "password": "1RhbhaTj1X",
    "region": ""
  },
  {
    "account": "heathereix65206@icloud.com",
    "password": "syj6pbsRqa",
    "region": ""
  },
  {
    "account": "etlbarbara90242@icloud.com",
    "password": "1dhykPhq8N",
    "region": ""
  },
  {
    "account": "o6gh6oby0f@icloud.com",
    "password": "BaR23FGKHH",
    "region": ""
  },
  {
    "account": "jeanavqq12970@icloud.com",
    "password": "tEvtPGB839",
    "region": ""
  },
  {
    "account": "andrewkeq32495@icloud.com",
    "password": "Wn9b7QwcpN",
    "region": ""
  },
  {
    "account": "embryn.sloan597@icloud.com",
    "password": "HfMt2@YO",
    "region": ""
  },
  {
    "account": "flhara.vale922@icloud.com",
    "password": "!vAt0yNn",
    "region": ""
  },
  {
    "account": "irowen.quinn216@icloud.com",
    "password": "g2ciLj@4",
    "region": ""
  },
  {
    "account": "julianmauhudson@outlook.com",
    "password": "TDMHQAgt2Rnw",
    "region": ""
  },
  {
    "account": "ashermendez4so@outlook.com",
    "password": "TDaWC3TfNNsT",
    "region": ""
  },
  {
    "account": "ojeovowc7810@hotmail.com",
    "password": "TD3DpSmctyXv",
    "region": ""
  },
  {
    "account": "eliasu2riley@outlook.com",
    "password": "TDU3vEMMkhjr",
    "region": ""
  },
  {
    "account": "wilmadaywaltqv@hotmail.com",
    "password": "TDWfjVRZ7u99",
    "region": ""
  },
  {
    "account": "alissascapin7639@icloud.com",
    "password": "gD#27HQe",
    "region": ""
  },
  {
    "account": "kyrarubel8805@icloud.com",
    "password": "xN#yK7w2",
    "region": ""
  },
  {
    "account": "melissacollhall2q8@icloud.com",
    "password": "h6@B6Zuo",
    "region": ""
  },
  {
    "account": "mepjkjy374417@icloud.com",
    "password": "HtE95GKheM",
    "region": ""
  },
  {
    "account": "othvtoh347353@icloud.com",
    "password": "N478zkt8KB",
    "region": ""
  },
  {
    "account": "mu894611708@icloud.com",
    "password": "9SZJ2JQreJ",
    "region": ""
  },
  {
    "account": "alswlln389627@icloud.com",
    "password": "fMaqzzeQ4F",
    "region": ""
  },
  {
    "account": "fugtdrn021306@icloud.com",
    "password": "aNg97DafXs",
    "region": ""
  },
  {
    "account": "ivxtirm369045@icloud.com",
    "password": "u3Uvjs39uX",
    "region": ""
  },
  {
    "account": "sjejxsq774991@icloud.com",
    "password": "ztVUH3G5rG",
    "region": ""
  },
  {
    "account": "nwqmlkm724113@icloud.com",
    "password": "JsJu1YNEvB",
    "region": ""
  },
  {
    "account": "bo402118157434@icloud.com",
    "password": "vcK4WZtgP5",
    "region": ""
  },
  {
    "account": "rwvidmf934559@icloud.com",
    "password": "8AhUaj3Mb1",
    "region": ""
  },
  {
    "account": "vvbwbyh472332@icloud.com",
    "password": "et9MXXKzkz",
    "region": ""
  },
  {
    "account": "ousdxpf261614@icloud.com",
    "password": "9yF3n4QwTv",
    "region": ""
  },
  {
    "account": "wu985826536225@icloud.com",
    "password": "entkMCaw44",
    "region": ""
  },
  {
    "account": "ipksauj788181@icloud.com",
    "password": "wcA49DVC63",
    "region": ""
  },
  {
    "account": "aocflno476251@icloud.com",
    "password": "w45pH3vWrq",
    "region": ""
  },
  {
    "account": "carmensur63212@icloud.com",
    "password": "1TaFZwtcTV",
    "region": ""
  },
  {
    "account": "jxjnhgu339891@icloud.com",
    "password": "dMYDxZ6EJf",
    "region": ""
  },
  {
    "account": "huai284600975@icloud.com",
    "password": "Ytj5aYUdT3",
    "region": ""
  },
  {
    "account": "zvmksii070361@icloud.com",
    "password": "zDjErZWM7g",
    "region": ""
  },
  {
    "account": "cou626674918404@icloud.com",
    "password": "QGU3GdU2xH",
    "region": ""
  },
  {
    "account": "kdzibli335026@icloud.com",
    "password": "nBzhj6eKs3",
    "region": ""
  },
  {
    "account": "ippekip345080@icloud.com",
    "password": "866Geaft9h",
    "region": ""
  },
  {
    "account": "li633563763@icloud.com",
    "password": "SSYQHGmZr4",
    "region": ""
  },
  {
    "account": "ehoviciwosibeb@email.com",
    "password": "2H8VTdNVTJ",
    "region": ""
  },
  {
    "account": "miwyxuqijo06@email.com",
    "password": "THfpZvG5bT",
    "region": ""
  },
  {
    "account": "sfavajilahuko91@email.com",
    "password": "CRnhzC5dXA",
    "region": ""
  },
  {
    "account": "wkyqenytus@email.com",
    "password": "MN1hR5NzWj",
    "region": ""
  },
  {
    "account": "wvrflnw523@outlook.com",
    "password": "TuytjzfT8R",
    "region": ""
  },
  {
    "account": "rowgxbyzpd556@outlook.com",
    "password": "46mRAZJ22k",
    "region": ""
  },
  {
    "account": "mcoebiur292@hotmail.com",
    "password": "5UvmNuqqf7",
    "region": ""
  },
  {
    "account": "lwxqhxtqf194@outlook.com",
    "password": "s54EFa6Auc",
    "region": ""
  },
  {
    "account": "quodonnell@gmail.com",
    "password": "Dd10096da",
    "region": ""
  },
  {
    "account": "david7zksmunoz@hotmail.com",
    "password": "TzTx3!zd",
    "region": ""
  },
  {
    "account": "DeborazpiHarr967@icloud.com",
    "password": "x5Qt9ch9m9",
    "region": ""
  },
  {
    "account": "jarvarisrivetteuf3409@gmail.com",
    "password": "VG7j2eeg4C",
    "region": ""
  },
  {
    "account": "AllenMilliepyl879@gmail.com",
    "password": "44s41NP3MD5pf3",
    "region": ""
  },
  {
    "account": "BettyGarcia5be56@gmail.com",
    "password": "44s4nrRa3yZnJ5",
    "region": ""
  },
  {
    "account": "rosskennedyjreg5953@gmail.com",
    "password": "De1Hm1h7a9",
    "region": ""
  },
  {
    "account": "VedderEarlrbpjhf@gmail.com",
    "password": "4PdNahXmqR",
    "region": ""
  },
  {
    "account": "andersenproschvc2764@gmail.com",
    "password": "FAy8cCAE8R",
    "region": ""
  },
  {
    "account": "michelleqmrwi3@gmail.com",
    "password": "gM7H6p96py",
    "region": ""
  },
  {
    "account": "uchtredmagowandf5018@gmail.com",
    "password": "Y3B9gtum4K",
    "region": ""
  },
  {
    "account": "jy359840651@163.com",
    "password": "Dd1927013",
    "region": ""
  },
  {
    "account": "kwopigk3809@163.com",
    "password": "Dd128c2e6",
    "region": ""
  },
  {
    "account": "jyvqvepn475@163.com",
    "password": "TDvU2c8Yw9Qr",
    "region": ""
  },
  {
    "account": "KevizpiMe644@icloud.com",
    "password": "jBh1Vj8EH3",
    "region": ""
  },
  {
    "account": "rowenawoodard246042b@icloud.com",
    "password": "BgW5juwnAt",
    "region": ""
  },
  {
    "account": "MirandzpiHugh848@icloud.com",
    "password": "spkV7Q52C1",
    "region": ""
  },
  {
    "account": "bradtnrosalbav39153@gmail.com",
    "password": "6jRNZT41Bm",
    "region": ""
  },
  {
    "account": "orprobeso50@outlook.com",
    "password": "6EJG1crZbk",
    "region": ""
  },
  {
    "account": "lambertruth282@gmail.com",
    "password": "2fCnKFRFKR",
    "region": ""
  },
  {
    "account": "PerezBettyzzd@gmail.com",
    "password": "98uXd9NR7w",
    "region": ""
  },
  {
    "account": "pamela53chadwickmjj@outlook.com",
    "password": "ef6BRTCpTj",
    "region": ""
  },
  {
    "account": "vgilesgh42@gmail.com",
    "password": "4HWwRkya6B",
    "region": ""
  },
  {
    "account": "ancq61nufio@gmail.com",
    "password": "Ma3ZMvZu2w",
    "region": ""
  },
  {
    "account": "tieshamorwaywi6420@gmail.com",
    "password": "6ZRcWustJ4",
    "region": ""
  },
  {
    "account": "robertwang380@gmail.com",
    "password": "fgKXq3uWA6",
    "region": ""
  },
  {
    "account": "stevensnjjt1@gmail.com",
    "password": "FP5a6bmVH4",
    "region": ""
  },
  {
    "account": "madelyncravenlgzx5364@gmail.com",
    "password": "vN151Vd7Dy",
    "region": ""
  },
  {
    "account": "owengkmkmoreno@hotmail.com",
    "password": "9dEHlMC\\u0026",
    "region": ""
  },
  {
    "account": "miastnley@gmail.com",
    "password": "Dd13c8e6d",
    "region": ""
  },
  {
    "account": "niuguadan31016@hotmail.com",
    "password": "nMF#Bhs0",
    "region": ""
  },
  {
    "account": "qian2007495zhan@163.com",
    "password": "CkMNTrafY8",
    "region": ""
  },
  {
    "account": "qfvblj2968@163.com",
    "password": "1qNQ2sDUJ1",
    "region": ""
  },
  {
    "account": "qgb477203@163.com",
    "password": "cZK7zCHkFF",
    "region": ""
  },
  {
    "account": "qfpcwzp942@163.com",
    "password": "mxhp8mP9BJ",
    "region": ""
  },
  {
    "account": "REBELPRIDE79@hotmail.com",
    "password": "6CFTdyJpNA",
    "region": ""
  },
  {
    "account": "diavl1b3@out1ok.com",
    "password": "e9CZYwTeBF",
    "region": ""
  },
  {
    "account": "ob471wj8@out1ok.com",
    "password": "q6gkZz9aKp",
    "region": ""
  },
  {
    "account": "gustave_cece_192.elwin899@outlook.es",
    "password": "c87pbcaxJU",
    "region": "美国"
  },
  {
    "account": "emilioh7pr40x@outlook.my",
    "password": "2fSvKdeEaT",
    "region": "美国"
  },
  {
    "account": "carmanhlo44746@icloud.com",
    "password": "QFcCetAWg1",
    "region": ""
  },
  {
    "account": "thnwcsd@outlook.com",
    "password": "vEgIGUGzQn6pm1wTq5OkVQ==",
    "region": "美国"
  },
  {
    "account": "anbrpggnr@outlook.com",
    "password": "Hdw+jFs9IwdT5t2eWCuJqQ==",
    "region": "美国"
  }
]