[
  {
    "account": "kasandracoffman93596@hotmail.com",
    "password": "uqtpdYdsn2",
    "region": ""
  },
  {
    "account": "alfiekysrobinsonbtn@gmail.com",
    "password": "6wykUFXPmw",
    "region": ""
  },
  {
    "account": "matthewmcbailey0j@gmail.com",
    "password": "HvY3tzXHtf",
    "region": ""
  },
  {
    "account": "maryamwkebrooksdtt@gmail.com",
    "password": "cb1qKsuS7J",
    "region": ""
  },
  {
    "account": "ryan2jqcookq7i@gmail.com",
    "password": "TDzBTPdpta4f",
    "region": ""
  },
  {
    "account": "freya1zjpattersonsu9@gmail.com",
    "password": "TDSp9uFmcWWr",
    "region": ""
  },
  {
    "account": "charlesbfpriveraxdx@gmail.com",
    "password": "TDUKpYZ5uzpd",
    "region": ""
  },
  {
    "account": "esmeihxwarduqf@gmail.com",
    "password": "TDRKTn52n7C5",
    "region": ""
  },
  {
    "account": "duchi838388@21cn.com",
    "password": "TDzzFChVfhC3",
    "region": ""
  },
  {
    "account": "zacharyiuacarterzma@gmail.com",
    "password": "TDHn6nSYZtvu",
    "region": ""
  },
  {
    "account": "yingmu16195184@21cn.com",
    "password": "TDQ5DXekwWE6",
    "region": ""
  },
  {
    "account": "chloedvpowellgl@gmail.com",
    "password": "hYRXgt5we4",
    "region": ""
  },
  {
    "account": "soikazleibysl@outlook.com",
    "password": "GB0Js5#0",
    "region": ""
  },
  {
    "account": "ameliascott5779@gmail.com",
    "password": "YJk3&8eK",
    "region": ""
  },
  {
    "account": "joychavez9761@gmail.com",
    "password": "Xe93Qm64",
    "region": "美国"
  },
  {
    "account": "lancerowe15958@gmail.com",
    "password": "Uh23Fm43",
    "region": "美国"
  },
  {
    "account": "antonioqmontgomeryu0h2b@gmail.com",
    "password": "Wa24Hx17",
    "region": "美国"
  },
  {
    "account": "finneywallace91167@gmail.com",
    "password": "Dp14Yx65",
    "region": "美国"
  },
  {
    "account": "agang130902783116@icloud.com",
    "password": "Dd18e8bb1",
    "region": ""
  },
  {
    "account": "hotcars964allison@icloud.com",
    "password": "Dd1ac323a",
    "region": ""
  },
  {
    "account": "vernaphillip750@gmail.com",
    "password": "whHEnXdPW2",
    "region": ""
  },
  {
    "account": "sa04gkacas585594@icloud.com",
    "password": "P2YvNWY1pc",
    "region": ""
  },
  {
    "account": "emilyjgcortiz01k@gmail.com",
    "password": "4ppveFux43",
    "region": ""
  },
  {
    "account": "bierospharet64905@icloud.com",
    "password": "cCdry3G1de",
    "region": "美国"
  },
  {
    "account": "queatnascet28@icloud.com",
    "password": "DP2cucSzsc",
    "region": "美国"
  },
  {
    "account": "umrho.ncus.mae381@icloud.com",
    "password": "n57EQFsEJX",
    "region": "美国"
  },
  {
    "account": "is.icura_bit48442@icloud.com",
    "password": "WmWf2aB757",
    "region": "美国"
  },
  {
    "account": "veren.merkson_ge4@icloud.com",
    "password": "vcVf6jkdW9",
    "region": "美国"
  },
  {
    "account": "pinedmaa@gmail.com",
    "password": "Dd1195012",
    "region": ""
  }
]