[
  {
    "account": "3392483535@qq.com",
    "password": "329s3Uky3s",
    "region": ""
  },
  {
    "account": "pharetran_ecin.ex28@icloud.com",
    "password": "CVzhj3wz93",
    "region": ""
  },
  {
    "account": "2696219804@qq.com",
    "password": "9Qju3JjkMx",
    "region": ""
  },
  {
    "account": "levinekeyla6870224@gmail.com",
    "password": "BvsgJX47Wf",
    "region": ""
  },
  {
    "account": "shaniceshelli@gmail.com",
    "password": "MsAtN4wXQC",
    "region": ""
  },
  {
    "account": "jonlucerofn531@gmail.com",
    "password": "gm3S6tSz2a",
    "region": ""
  },
  {
    "account": "3498871513@qq.com",
    "password": "CGMUR8BKCt",
    "region": ""
  },
  {
    "account": "ww0tG14HQHU311@hotmail.com",
    "password": "RD3MjrevTv",
    "region": ""
  },
  {
    "account": "elizaqroriverafkr@gmail.com",
    "password": "HU8CdnR7wZ",
    "region": ""
  },
  {
    "account": "Tibbetts3052mrkl@gmail.com",
    "password": "cAFj48KpuD",
    "region": ""
  },
  {
    "account": "ptxrff@163.com",
    "password": "RXgZtDU4We",
    "region": ""
  },
  {
    "account": "Leclair0509yel@gmail.com",
    "password": "8rxm4TgtB8",
    "region": ""
  },
  {
    "account": "umyhrmvkq@hotmail.com",
    "password": "TDCjvESV6vDP",
    "region": ""
  },
  {
    "account": "ehfgwdpwg@outlook.com",
    "password": "rZDWx!L6",
    "region": ""
  },
  {
    "account": "avinejygere1967@outlook.com",
    "password": "Gz8&wW3Z",
    "region": ""
  },
  {
    "account": "gamblecarolyn996@gmail.com",
    "password": "@pm@4KGF",
    "region": ""
  },
  {
    "account": "agang130902783116@icloud.com",
    "password": "Dd18add87",
    "region": ""
  },
  {
    "account": "hotcars964allison@icloud.com",
    "password": "Dd157a4eb",
    "region": ""
  },
  {
    "account": "ragamat1503510n@icloud.com",
    "password": "Dd121bb34",
    "region": ""
  },
  {
    "account": "queatnascet28@icloud.com",
    "password": "G4p8XTUAus",
    "region": "美国"
  },
  {
    "account": "veren.merkson_ge4@icloud.com",
    "password": "JEadS18e8Y",
    "region": "美国"
  },
  {
    "account": "is.icura_bit48442@icloud.com",
    "password": "rbGPfYS2Mc",
    "region": "美国"
  },
  {
    "account": "bierospharet64905@icloud.com",
    "password": "UqU8GZ12f1",
    "region": "美国"
  },
  {
    "account": "umrho.ncus.mae381@icloud.com",
    "password": "C2UwvUGfQM",
    "region": "美国"
  },
  {
    "account": "monroealexis618@gmail.com",
    "password": "kN1qk6wrcB",
    "region": ""
  },
  {
    "account": "bellasantos57914@gmail.com",
    "password": "aTr3jk4Ynt",
    "region": ""
  },
  {
    "account": "darleneccolemansagrc@gmail.com",
    "password": "5hW5pHzDUY",
    "region": ""
  },
  {
    "account": "Gomez0509yel@gmail.com",
    "password": "Fcz1NcTr9F",
    "region": ""
  },
  {
    "account": "k73trd@163.com",
    "password": "UqnRSPkK7F",
    "region": ""
  },
  {
    "account": "etusdonecsus79916@icloud.com",
    "password": "3jMEkGaZsW",
    "region": ""
  },
  {
    "account": "Kingsley0509yel@gmail.com",
    "password": "MBbN8542",
    "region": ""
  },
  {
    "account": "duoctotlamsacmatcokhong@gmail.com",
    "password": "2FJ!Ymx1",
    "region": ""
  },
  {
    "account": "cranstondittoahmpfl1e163q@outlook.com",
    "password": "@ajX08Sm",
    "region": ""
  },
  {
    "account": "albaballasikvz0z0jdhwiao5@outlook.com",
    "password": "vm1g0x@T",
    "region": ""
  },
  {
    "account": "tim6031jordan@yandex.com",
    "password": "\\u0026i26Mzcb",
    "region": ""
  },
  {
    "account": "terri7035hayes@yandex.com",
    "password": "vap9Zj#C",
    "region": ""
  },
  {
    "account": "vxzlxoi1176y@outlook.com",
    "password": "X48sC9wGwV",
    "region": "美国"
  },
  {
    "account": "yrdjdariofisher@gmail.com",
    "password": "1wqJRjkZQ5",
    "region": "美国"
  },
  {
    "account": "laurenstierjq7035@gmail.com",
    "password": "HEuQnH9WBa",
    "region": "美国"
  },
  {
    "account": "azumi.bhoomr6@icloud.com",
    "password": "1Amdd8NH7a",
    "region": "美国"
  },
  {
    "account": "sarahdoolittle551881@gmail.com",
    "password": "EmbQJcyS5y",
    "region": "美国"
  }
]